django_silque_notifications-0.1.1.dist-info/licenses/LICENSE
silque_notifications/__init__.py
silque_notifications/admin.py
silque_notifications/apps.py
silque_notifications/backends.py
silque_notifications/base_admin.py
silque_notifications/forms.py
silque_notifications/helpers.py
silque_notifications/models.py
silque_notifications/services.py
silque_notifications/signals.py
silque_notifications/tasks.py
silque_notifications/tests.py
silque_notifications/urls.py
silque_notifications/views.py
silque_notifications/management/__init__.py
silque_notifications/management/commands/__init__.py
silque_notifications/management/commands/test_celery_notifications.py
silque_notifications/migrations/0001_initial.py
silque_notifications/migrations/__init__.py
silque_notifications/static/silque_notifications/notification_admin.js
silque_notifications/static/silque_notifications/recipients_admin.js
silque_notifications/static/silque_notifications/css/notification_admin.css
silque_notifications/static/silque_notifications/js/notification_admin.js
silque_notifications/templates/admin/silque_notifications/notification/change_form.html
silque_notifications/templates/notification/change_form.html
django_silque_notifications-0.1.1.dist-info/METADATA
django_silque_notifications-0.1.1.dist-info/WHEEL
django_silque_notifications-0.1.1.dist-info/top_level.txt
django_silque_notifications-0.1.1.dist-info/RECORD
