Metadata-Version: 2.4
Name: django-silque-notifications
Version: 0.1.1
Summary: Flexible, admin-driven notifications for Django with Celery/Redis, relational recipients, and templating.
Author: Silquetech
License:                     GNU AFFERO GENERAL PUBLIC LICENSE
Project-URL: Homepage, https://github.com/Silquetech/django-silque-notifications
Project-URL: Repository, https://github.com/Silquetech/django-silque-notifications
Project-URL: Issues, https://github.com/Silquetech/django-silque-notifications/issues
Keywords: django,notifications,celery,redis,email,sms,whatsapp
Classifier: Development Status :: 3 - Alpha
Classifier: Framework :: Django
Classifier: Framework :: Django :: 4.2
Classifier: Framework :: Django :: 5.0
Classifier: Intended Audience :: Developers
Classifier: License :: OSI Approved :: GNU Affero General Public License v3 or later (AGPLv3+)
Classifier: Programming Language :: Python
Classifier: Programming Language :: Python :: 3
Classifier: Programming Language :: Python :: 3 :: Only
Classifier: Programming Language :: Python :: 3.10
Classifier: Programming Language :: Python :: 3.11
Classifier: Programming Language :: Python :: 3.12
Classifier: Programming Language :: Python :: 3.13
Classifier: Topic :: Communications
Classifier: Topic :: Communications :: Email
Classifier: Topic :: Software Development :: Libraries :: Python Modules
Requires-Python: >=3.10
License-File: LICENSE
Requires-Dist: Django>=4.2
Requires-Dist: celery>=5.3
Requires-Dist: redis>=4
Provides-Extra: dev
Requires-Dist: ruff>=0.6; extra == "dev"
Requires-Dist: mypy>=1.10; extra == "dev"
Requires-Dist: pytest>=8; extra == "dev"
Requires-Dist: pytest-django>=4.8; extra == "dev"
Requires-Dist: tox>=4; extra == "dev"
Requires-Dist: types-redis; extra == "dev"
Dynamic: license-file
